viledatools/__init__.py
viledatools/apiutils.py
viledatools/diagonaltablewalk.py
viledatools/fatask.py
viledatools/importcellparser.py
viledatools/importsheetparser.py
viledatools/viledaexceptions.py
viledatools/viledautils.py
viledatools-1.0.44.dist-info/LICENSE.txt
viledatools-1.0.44.dist-info/METADATA
viledatools-1.0.44.dist-info/WHEEL
viledatools-1.0.44.dist-info/top_level.txt
viledatools-1.0.44.dist-info/RECORD
