Metadata-Version: 2.1
Name: viledatools
Version: 1.0.44
Summary: Classes and functions to use for development of intregration software
Home-page: https://www.vileda-professional.com/
Author: FHCS GmbH
Author-email: support@fhcs.zendesk.com
License: Creative Commons Attribution 4.0 International
Classifier: Development Status :: 4 - Beta
Classifier: Environment :: Other Environment
Classifier: License :: Other/Proprietary License
Classifier: Natural Language :: English
Classifier: Programming Language :: Python :: 3
Classifier: Programming Language :: Python :: 3.8
Classifier: Topic :: Utilities
Requires-Python: >=3.8
License-File: LICENSE.txt
Requires-Dist: aiohttp (>=3.8.3)
Requires-Dist: openpyxl (>=3.0.10)
